{"is_source_file": false, "format": "", "description": "", "external_files": [], "external_methods": [], "published": [], "classes": [], "methods": [], "calls": [], "search-terms": [], "state": 2, "file_id": 2, "knowledge_revision": 40, "git_revision": "6f866c5647488df898439c95ffa2a9f133dd7c2a", "hash": "daab40a535f11e8cd6f4ff86bea5197b", "format-version": 4, "code-base-name": "mobile_frontend", "filename": "mobile_frontend/app.json", "revision_history": [{"40": "6f866c5647488df898439c95ffa2a9f133dd7c2a"}]}